wia_scan/__init__.py
wia_scan/core.py
wia_scan/main.py
wia_scan-0.8.0.dist-info/entry_points.txt
wia_scan-0.8.0.dist-info/LICENSE
wia_scan-0.8.0.dist-info/WHEEL
wia_scan-0.8.0.dist-info/METADATA
wia_scan-0.8.0.dist-info/RECORD
