Metadata-Version: 2.1
Name: wia_scan
Version: 0.8.0
Summary: wia_scan 0.8.0
Author-email: Jonas Zehnder <12305646+JonasZehn@users.noreply.github.com>
Requires-Python: >=3.7
Classifier: Programming Language :: Python :: 3
Classifier: License :: OSI Approved :: MIT License
Classifier: Natural Language :: English
Classifier: Operating System :: Microsoft :: Windows
Requires-Dist: pywin32
Requires-Dist: Pillow
Requires-Dist: numpy
Requires-Dist: docopt
Requires-Dist: bumpver ; extra == "dev"
Requires-Dist: pip-tools ; extra == "dev"
Requires-Dist: pytest ; extra == "dev"
Requires-Dist: mock ; extra == "dev"
Project-URL: Home, https://github.com/JonasZehn/python_wia_scan
Project-URL: Source, https://github.com/JonasZehn/python_wia_scan
Provides-Extra: dev
